odoo/addons/stock_landed_costs_purchase_auto/README.rst
odoo/addons/stock_landed_costs_purchase_auto/__init__.py
odoo/addons/stock_landed_costs_purchase_auto/__manifest__.py
odoo/addons/stock_landed_costs_purchase_auto/i18n/es.po
odoo/addons/stock_landed_costs_purchase_auto/i18n/stock_landed_costs_purchase_auto.pot
odoo/addons/stock_landed_costs_purchase_auto/models/__init__.py
odoo/addons/stock_landed_costs_purchase_auto/models/purchase_order.py
odoo/addons/stock_landed_costs_purchase_auto/models/stock_landed_cost.py
odoo/addons/stock_landed_costs_purchase_auto/readme/CONTRIBUTORS.rst
odoo/addons/stock_landed_costs_purchase_auto/readme/DESCRIPTION.rst
odoo/addons/stock_landed_costs_purchase_auto/readme/USAGE.rst
odoo/addons/stock_landed_costs_purchase_auto/static/description/icon.png
odoo/addons/stock_landed_costs_purchase_auto/static/description/index.html
odoo/addons/stock_landed_costs_purchase_auto/tests/__init__.py
odoo/addons/stock_landed_costs_purchase_auto/tests/test_purchase_order.py
odoo/addons/stock_landed_costs_purchase_auto/views/purchase_order_view.xml
odoo/addons/stock_landed_costs_purchase_auto/views/stock_landed_cost_view.xml
odoo13_addon_stock_landed_costs_purchase_auto-13.0.1.0.1.dev4.dist-info/METADATA
odoo13_addon_stock_landed_costs_purchase_auto-13.0.1.0.1.dev4.dist-info/WHEEL
odoo13_addon_stock_landed_costs_purchase_auto-13.0.1.0.1.dev4.dist-info/top_level.txt
odoo13_addon_stock_landed_costs_purchase_auto-13.0.1.0.1.dev4.dist-info/RECORD
